LICENSE
MANIFEST.in
setup.cfg
setup.py
chainer/__init__.py
chainer/_backprop_utils.py
chainer/_environment_check.py
chainer/_runtime_info.py
chainer/_version.py
chainer/computational_graph.py
chainer/configuration.py
chainer/cuda.py
chainer/function.py
chainer/function_hook.py
chainer/function_node.py
chainer/gradient_check.py
chainer/initializer.py
chainer/link.py
chainer/log.py
chainer/optimizer.py
chainer/reporter.py
chainer/sequential.py
chainer/serializer.py
chainer/variable.py
chainer/backends/__init__.py
chainer/backends/cuda.py
chainer/backends/cuda_fusion.py
chainer/backends/intel64.py
chainer/dataset/__init__.py
chainer/dataset/convert.py
chainer/dataset/dataset_mixin.py
chainer/dataset/download.py
chainer/dataset/iterator.py
chainer/datasets/__init__.py
chainer/datasets/_mnist_helper.py
chainer/datasets/cifar.py
chainer/datasets/concatenated_dataset.py
chainer/datasets/dict_dataset.py
chainer/datasets/fashion_mnist.py
chainer/datasets/image_dataset.py
chainer/datasets/mnist.py
chainer/datasets/ptb.py
chainer/datasets/sub_dataset.py
chainer/datasets/svhn.py
chainer/datasets/transform_dataset.py
chainer/datasets/tuple_dataset.py
chainer/exporters/__init__.py
chainer/exporters/caffe.py
chainer/function_hooks/__init__.py
chainer/function_hooks/cuda_profile.py
chainer/function_hooks/cupy_memory_profile.py
chainer/function_hooks/debug_print.py
chainer/function_hooks/timer.py
chainer/functions/__init__.py
chainer/functions/activation/__init__.py
chainer/functions/activation/clipped_relu.py
chainer/functions/activation/crelu.py
chainer/functions/activation/elu.py
chainer/functions/activation/hard_sigmoid.py
chainer/functions/activation/leaky_relu.py
chainer/functions/activation/log_softmax.py
chainer/functions/activation/lstm.py
chainer/functions/activation/maxout.py
chainer/functions/activation/prelu.py
chainer/functions/activation/relu.py
chainer/functions/activation/selu.py
chainer/functions/activation/sigmoid.py
chainer/functions/activation/slstm.py
chainer_ibmopt.egg-info/PKG-INFO
chainer_ibmopt.egg-info/SOURCES.txt
chainer_ibmopt.egg-info/dependency_links.txt
chainer_ibmopt.egg-info/not-zip-safe
chainer_ibmopt.egg-info/requires.txt
chainer_ibmopt.egg-info/top_level.txt