Metadata-Version: 1.0
Name: chainer-ibmopt
Version: 4.0.0a3
Summary: A flexible framework of neural networks (opbimized for POWER machines by IBM)
Home-page: https://chainer.org/
Author: Seiya Tokui
Author-email: tokui@preferred.jp
License: MIT License
Platform: UNKNOWN
